[
  {"tool": "compare_files", "input": {"left_path": "C:/a.txt", "right_path": "C:/b.txt"}, "output": {"success": true, "identical": false, "differences_found": true}},
  {"tool": "compare_files", "input": {"left_path": "C:/a.txt", "right_path": "C:/a_copy.txt"}, "output": {"success": true, "identical": true, "differences_found": false}},
  {"tool": "compare_files", "input": {"left_path": "C:/old.py", "right_path": "C:/new.py", "output_report": "C:/diff.txt"}, "output": {"success": true, "differences_found": true}},
  {"tool": "compare_files", "input": {"left_path": "C:/missing.txt", "right_path": "C:/b.txt"}, "output": {"success": false, "error": "Left file not found"}},
  {"tool": "compare_files", "input": {"left_path": "C:/a.txt", "right_path": "C:/missing.txt"}, "output": {"success": false, "error": "Right file not found"}},
  {"tool": "compare_folders", "input": {"left_path": "C:/folder_a", "right_path": "C:/folder_b"}, "output": {"success": true, "differences_found": true}},
  {"tool": "compare_folders", "input": {"left_path": "C:/folder_a", "right_path": "C:/folder_b", "include_subfolders": false}, "output": {"success": true, "differences_found": true}},
  {"tool": "compare_folders", "input": {"left_path": "C:/a", "right_path": "C:/a_copy"}, "output": {"success": true, "differences_found": false}},
  {"tool": "compare_folders", "input": {"left_path": "C:/a", "right_path": "C:/b", "output_report": "C:/r.txt"}, "output": {"success": true}},
  {"tool": "compare_folders", "input": {"left_path": "C:/missing", "right_path": "C:/b"}, "output": {"success": false, "error": "Left folder not found"}},
  {"tool": "sync_folders", "input": {"source_path": "C:/src", "target_path": "D:/dst", "sync_mode": "mirror", "dry_run": true}, "output": {"success": true, "changes_detected": true}},
  {"tool": "sync_folders", "input": {"source_path": "C:/src", "target_path": "D:/dst", "sync_mode": "mirror", "dry_run": false}, "output": {"success": true, "changes_detected": true}},
  {"tool": "sync_folders", "input": {"source_path": "C:/src", "target_path": "D:/dst", "sync_mode": "update", "dry_run": true}, "output": {"success": true}},
  {"tool": "sync_folders", "input": {"source_path": "C:/src", "target_path": "D:/dst", "sync_mode": "update", "dry_run": false}, "output": {"success": true}},
  {"tool": "sync_folders", "input": {"source_path": "C:/src", "target_path": "D:/dst", "sync_mode": "backup", "dry_run": true}, "output": {"success": true}},
  {"tool": "sync_folders", "input": {"source_path": "C:/src", "target_path": "D:/dst", "sync_mode": "backup", "dry_run": false}, "output": {"success": true}},
  {"tool": "sync_folders", "input": {"source_path": "C:/missing", "target_path": "D:/dst"}, "output": {"success": false, "error": "Source folder not found"}},
  {"tool": "sync_folders", "input": {"source_path": "C:/src", "target_path": "D:/dst", "sync_mode": "invalid"}, "output": {"success": false, "error": "Invalid sync mode"}},
  {"tool": "multimedia_drive_scanner", "input": {}, "output": {"success": true, "total_files": 10000, "total_size_gb": 200.5}},
  {"tool": "multimedia_drive_scanner", "input": {"drives": ["E:", "F:"]}, "output": {"success": true, "drives_scanned": ["E:", "F:"]}},
  {"tool": "multimedia_drive_scanner", "input": {"file_types": ["video"]}, "output": {"success": true, "total_files": 5000}},
  {"tool": "multimedia_drive_scanner", "input": {"file_types": ["audio"]}, "output": {"success": true, "total_files": 3000}},
  {"tool": "multimedia_drive_scanner", "input": {"file_types": ["images"]}, "output": {"success": true, "total_files": 1500}},
  {"tool": "multimedia_drive_scanner", "input": {"recent_days": 7}, "output": {"success": true, "total_files": 100}},
  {"tool": "multimedia_drive_scanner", "input": {"drives": ["E:"], "recent_days": 30, "file_types": ["video", "audio"]}, "output": {"success": true}},
  {"tool": "multimedia_drive_scanner", "input": {"drives": ["X:"]}, "output": {"success": false, "error": "No multimedia drives found"}},
  {"tool": "find_multimedia_duplicates", "input": {}, "output": {"success": true, "total_duplicate_groups": 10, "total_savings_gb": 5.0}},
  {"tool": "find_multimedia_duplicates", "input": {"use_content_hash": true}, "output": {"success": true, "detection_method": "content_hash"}},
  {"tool": "find_multimedia_duplicates", "input": {"use_content_hash": false}, "output": {"success": true, "detection_method": "name_and_size"}},
  {"tool": "find_multimedia_duplicates", "input": {"min_size_mb": 100}, "output": {"success": true, "total_duplicate_groups": 2}},
  {"tool": "find_multimedia_duplicates", "input": {"min_size_mb": 0.1, "file_types": ["video"]}, "output": {"success": true}},
  {"tool": "find_multimedia_duplicates", "input": {"drives": ["E:", "F:"], "use_content_hash": false}, "output": {"success": true}},
  {"tool": "detect_usb_drives", "input": {}, "output": {"success": true, "count": 2, "usb_drives": [{"drive_letter": "G:", "label": "USB DRIVE"}]}},
  {"tool": "detect_usb_drives", "input": {}, "output": {"success": true, "count": 0, "usb_drives": []}},
  {"tool": "detect_usb_drives", "input": {}, "output": {"success": true, "count": 1, "usb_drives": [{"drive_letter": "H:", "label": "BACKUP"}]}},
  {"tool": "backup_dev_repositories", "input": {"repo_paths": ["D:/Dev/repos/project-a", "D:/Dev/repos/project-b"]}, "output": {"success": true, "backup_count": 2}},
  {"tool": "backup_dev_repositories", "input": {"output_dir": "D:/backups/repos"}, "output": {"success": true, "backup_count": 5}},
  {"tool": "backup_dev_repositories", "input": {"exclude_patterns": ["*.log", "tmp/"]}, "output": {"success": true}},
  {"tool": "backup_dev_repositories", "input": {}, "output": {"success": true, "backup_count": 10, "total_size_mb": 500.0}},
  {"tool": "analyze_dev_workspace", "input": {"workspace_path": "D:/Dev/repos"}, "output": {"success": true, "total_repos": 25, "total_loc": 100000}},
  {"tool": "analyze_dev_workspace", "input": {"workspace_path": "D:/Dev", "depth": 1}, "output": {"success": true, "total_repos": 5}},
  {"tool": "analyze_dev_workspace", "input": {"depth": 4}, "output": {"success": true, "languages": {"Python": {"repos": 10}}}},
  {"tool": "scan_repo_health", "input": {"repo_path": "D:/Dev/repos/project"}, "output": {"success": true, "status": "healthy", "issues": {}}},
  {"tool": "scan_repo_health", "input": {"repo_path": "D:/Dev/repos/project"}, "output": {"success": true, "status": "needs_attention"}},
  {"tool": "scan_repo_health", "input": {"repo_path": "D:/Dev/repos/project", "auto_fix": true}, "output": {"success": true}},
  {"tool": "scan_repo_health", "input": {"repo_path": "D:/Dev/repos/project"}, "output": {"success": true, "issues": {"dirty_git": true, "unpushed_commits": 5}}},
  {"tool": "cleanup_dev_artifacts", "input": {"workspace_path": "D:/Dev/repos", "dry_run": true}, "output": {"success": true, "artifacts_found": 15}},
  {"tool": "cleanup_dev_artifacts", "input": {"workspace_path": "D:/Dev/repos", "dry_run": false}, "output": {"success": true, "artifacts_found": 15}},
  {"tool": "cleanup_dev_artifacts", "input": {"dry_run": true, "min_size_mb": 100}, "output": {"success": true, "artifacts_found": 3}},
  {"tool": "cleanup_dev_artifacts", "input": {"dry_run": false}, "output": {"success": true, "potential_savings_gb": 2.5}},
  {"tool": "cleanup_dev_artifacts", "input": {"patterns": ["node_modules", ".next"]}, "output": {"success": true}},
  {"tool": "find_duplicate_code", "input": {"workspace_path": "D:/Dev/repos"}, "output": {"success": true, "refactoring_opportunities": 5}},
  {"tool": "find_duplicate_code", "input": {"workspace_path": "D:/Dev/repos", "min_lines": 20}, "output": {"success": true, "duplicate_blocks": []}},
  {"tool": "find_duplicate_code", "input": {"workspace_path": "D:/Dev/repos", "extensions": [".py"]}, "output": {"success": true}},
  {"tool": "find_duplicate_code", "input": {"workspace_path": "D:/Dev", "exclude_patterns": ["vendor", "third_party"]}, "output": {"success": true}},
  {"tool": "compare_workspace_snapshots", "input": {"snapshot_a": "C:/before.json", "snapshot_b": "C:/after.json"}, "output": {"success": true, "added": 5, "removed": 2, "modified": 3}},
  {"tool": "compare_workspace_snapshots", "input": {"snapshot_a": "C:/v1.json", "snapshot_b": "C:/v2.json", "report_format": "detailed"}, "output": {"success": true}},
  {"tool": "compare_workspace_snapshots", "input": {"snapshot_a": "C:/empty_before.json", "snapshot_b": "C:/empty_after.json"}, "output": {"success": true, "unchanged": 100}},
  {"tool": "selective_restore", "input": {"backup_path": "C:/backup.zip", "restore_path": "D:/restored"}, "output": {"success": true, "files_restored": 50}},
  {"tool": "selective_restore", "input": {"backup_path": "C:/backup.zip", "restore_path": "D:/restored", "patterns": ["src/**"]}, "output": {"success": true, "files_restored": 30}},
  {"tool": "selective_restore", "input": {"backup_path": "C:/backup.zip", "restore_path": "D:/restored", "overwrite": true}, "output": {"success": true}},
  {"tool": "selective_restore", "input": {"backup_path": "C:/missing.zip", "restore_path": "D:/restored"}, "output": {"success": false, "error": "Backup not found"}},
  {"tool": "beyondcompare_agentic_workflow", "input": {"workflow_prompt": "Compare src folders of project-a and project-b"}, "output": {"success": true, "steps": []}},
  {"tool": "beyondcompare_agentic_workflow", "input": {"workflow_prompt": "Scan multimedia drives and find duplicates"}, "output": {"success": true, "steps": []}},
  {"tool": "beyondcompare_agentic_workflow", "input": {"workflow_prompt": "Check repo health of all repos in workspace"}, "output": {"success": true}},
  {"tool": "beyondcompare_sampling_hint", "input": {}, "output": {"success": true, "available_tools": ["compare_files", "compare_folders", "sync_folders"]}},
  {"tool": "beyondcompare_sampling_hint", "input": {}, "output": {"success": true, "message": "Sampling requires FastMCP 3.1+"}},
  {"tool": "multimedia_drive_scanner", "input": {"drives": ["K:", "L:"], "file_types": ["documents"]}, "output": {"success": true}},
  {"tool": "multimedia_drive_scanner", "input": {"drives": ["F:"], "recent_days": 14}, "output": {"success": true}},
  {"tool": "multimedia_drive_scanner", "input": {"file_types": ["video", "audio", "images", "documents"]}, "output": {"success": true}},
  {"tool": "find_multimedia_duplicates", "input": {"file_types": ["video"], "min_size_mb": 50}, "output": {"success": true}},
  {"tool": "find_multimedia_duplicates", "input": {"drives": ["E:"], "use_content_hash": true, "min_size_mb": 1}, "output": {"success": true}},
  {"tool": "find_multimedia_duplicates", "input": {}, "output": {"success": true, "duplicate_groups": [{"size_mb": 500, "duplicate_count": 2, "files": [{"name": "movie.mp4", "drive": "E:"}, {"name": "movie.mp4", "drive": "F:"}]}]}},
  {"tool": "analyze_dev_workspace", "input": {}, "output": {"success": true, "total_repos": 0}},
  {"tool": "analyze_dev_workspace", "input": {"workspace_path": "D:/Dev", "depth": 5}, "output": {"success": true}},
  {"tool": "scan_repo_health", "input": {}, "output": {"success": true, "status": "healthy"}},
  {"tool": "scan_repo_health", "input": {"repo_path": "D:/Dev/repos/broken"}, "output": {"success": true, "status": "needs_attention", "issues": {"missing_tests": true}}},
  {"tool": "scan_repo_health", "input": {"auto_fix": false}, "output": {"success": true, "suggestions": ["Update dependencies"]}},
  {"tool": "cleanup_dev_artifacts", "input": {}, "output": {"success": true}},
  {"tool": "cleanup_dev_artifacts", "input": {"dry_run": true, "workspace_path": "D:/Dev/repos/project-a"}, "output": {"success": true}},
  {"tool": "find_duplicate_code", "input": {}, "output": {"success": true, "total_files_scanned": 500}},
  {"tool": "find_duplicate_code", "input": {"min_lines": 5, "extensions": [".rs"]}, "output": {"success": true}},
  {"tool": "find_duplicate_code", "input": {"extensions": [".py"]}, "output": {"success": true}},
  {"tool": "compare_workspace_snapshots", "input": {"snapshot_a": "C:/s1.json", "snapshot_b": "C:/s2.json"}, "output": {"success": true, "added": 10, "removed": 0, "modified": 0}},
  {"tool": "compare_workspace_snapshots", "input": {"snapshot_a": "C:/s1.json", "snapshot_b": "C:/s2.json", "report_format": "summary"}, "output": {"success": true}},
  {"tool": "selective_restore", "input": {"backup_path": "C:/backup.zip", "restore_path": "D:/out", "patterns": ["*.txt"]}, "output": {"success": true, "files_restored": 5}},
  {"tool": "selective_restore", "input": {"backup_path": "C:/backup.zip", "restore_path": "D:/out", "overwrite": false}, "output": {"success": true}},
  {"tool": "backup_dev_repositories", "input": {"repo_paths": ["D:/Dev/repos/my-project"]}, "output": {"success": true, "backup_count": 1, "total_size_mb": 50}},
  {"tool": "backup_dev_repositories", "input": {}, "output": {"success": true, "total_size_mb": 1000}},
  {"tool": "backup_dev_repositories", "input": {"exclude_patterns": [".git"]}, "output": {"success": true}},
  {"tool": "detect_usb_drives", "input": {}, "output": {"success": true, "usb_drives": [{"drive_letter": "I:", "label": "EXT_DRIVE"}]}},
  {"tool": "detect_usb_drives", "input": {}, "output": {"success": false, "message": "USB drive detection failed"}},
  {"tool": "sync_folders", "input": {"source_path": "C:/src", "target_path": "D:/dst", "sync_mode": "mirror"}, "output": {"success": true}},
  {"tool": "compare_folders", "input": {"left_path": "C:/a", "right_path": "C:/b", "output_report": "C:/r.html"}, "output": {"success": true}},
  {"tool": "compare_files", "input": {"left_path": "C:/a.json", "right_path": "C:/b.json"}, "output": {"success": true, "identical": true}},
  {"tool": "compare_files", "input": {"left_path": "C:/a.xml", "right_path": "C:/b.xml", "output_report": "C:/diff.xml"}, "output": {"success": true, "differences_found": true}},
  {"tool": "compare_files", "input": {"left_path": "C:/code/v1.py", "right_path": "C:/code/v2.py"}, "output": {"success": true, "identical": false, "differences_found": true, "message": "Differences found between files"}},
  {"tool": "compare_files", "input": {"left_path": "C:/data.json", "right_path": "C:/data_copy.json"}, "output": {"success": true, "identical": true, "message": "Files are identical"}},
  {"tool": "compare_folders", "input": {"left_path": "C:/backup/week1", "right_path": "C:/backup/week2", "output_report": "C:/rpt.txt"}, "output": {"success": true, "differences_found": true, "include_subfolders": true}},
  {"tool": "compare_folders", "input": {"left_path": "C:/empty", "right_path": "C:/empty_copy"}, "output": {"success": true, "differences_found": false}},
  {"tool": "sync_folders", "input": {"source_path": "C:/projects/myapp", "target_path": "D:/backups/myapp", "sync_mode": "mirror", "dry_run": false}, "output": {"success": true, "changes_detected": true, "message": "Synchronization completed successfully"}},
  {"tool": "multimedia_drive_scanner", "input": {"file_types": ["images"], "recent_days": 90}, "output": {"success": true, "total_files": 5000}},
  {"tool": "detect_usb_drives", "input": {}, "output": {"success": true, "count": 3, "usb_drives": [{"drive_letter": "G:", "label": "DRIVE1"}, {"drive_letter": "H:", "label": "DRIVE2"}, {"drive_letter": "I:", "label": "DRIVE3"}]}},
  {"tool": "find_duplicate_code", "input": {"workspace_path": "D:/Dev/repos", "min_lines": 30}, "output": {"success": true, "total_files_scanned": 1500, "refactoring_opportunities": 2}}
]
